[
  {
    "id": "ADR-20260307-0011",
    "title": "Exclusion defaults consolidation into a program set",
    "tags": [
      "sync-task",
      "exclusion",
      "migration",
      "config-store",
      "ux",
      "macos",
      "tauri"
    ],
    "status": "Accepted",
    "date": "2026-03-07",
    "tldr": "Replace per-ecosystem built-in exclusion defaults with one `program` built-in set, automatically migrate legacy built-in IDs in stored exclusion sets and tasks, and remove `.gitignore` from the `git` built-in set.",
    "path": "doc/adr/ADR-20260307-0011-PRG-exclusion-defaults-consolidation-into-program.md"
  },
  {
    "id": "ADR-20260306-0010",
    "title": "Enabled-only MCP relay for a running-app control plane",
    "tags": [
      "mcp",
      "control-plane",
      "config-store",
      "runtime",
      "tauri",
      "macos"
    ],
    "status": "Accepted",
    "date": "2026-03-06",
    "tldr": "Expose a local stdio MCP relay only when the user explicitly enables MCP in SyncWatcher settings, and route all MCP actions through the running app backend over a Unix socket with backend-owned canonical config.",
    "path": "doc/adr/ADR-20260306-0010-MCP-enabled-running-app-control-plane.md"
  },
  {
    "id": "ADR-20260305-0009",
    "title": "Release SBOM generation and optional cosign attestation",
    "tags": [
      "release",
      "security",
      "sbom",
      "attestation",
      "ci",
      "supply-chain"
    ],
    "status": "Accepted",
    "date": "2026-03-05",
    "tldr": "Generate CycloneDX/SPDX SBOMs on tagged releases, attach them as release assets, and optionally produce keyless cosign attestations for shipped binaries.",
    "path": "doc/adr/ADR-20260305-0009-release-sbom-and-optional-cosign-attestation.md"
  },
  {
    "id": "ADR-20260301-0008",
    "title": "watchMode zero-copy auto-unmount deferred confirmation",
    "tags": [
      "watch-mode",
      "auto-unmount",
      "ux",
      "notification",
      "safety",
      "macos"
    ],
    "status": "Accepted",
    "date": "2026-03-01",
    "tldr": "When watch sync copies zero files, replace immediate auto-unmount with notification + deferred in-app confirmation, and unmount only after explicit approval.",
    "path": "doc/adr/ADR-20260301-0008-watchmode-zero-copy-auto-unmount-deferred-confirm.md"
  },
  {
    "id": "ADR-20260228-0007",
    "title": "Exclusion template expansion and exclusion-pattern limit increase",
    "tags": [
      "sync-task",
      "exclusion",
      "templates",
      "reliability",
      "performance",
      "macos",
      "tauri"
    ],
    "status": "Accepted",
    "date": "2026-02-28",
    "tldr": "Expand default exclusion templates across major ecosystems, merge missing defaults for existing users once, and raise exclusion-pattern limit from 100 to 300 with runtime deduplication.",
    "path": "doc/adr/ADR-20260228-0007-exclusion-template-expansion-and-pattern-limit.md"
  },
  {
    "id": "ADR-20260227-0006",
    "title": "Target-newer conflict hash-equivalence exception",
    "tags": [
      "sync-task",
      "safety",
      "conflict-review",
      "checksum",
      "macos",
      "tauri"
    ],
    "status": "Accepted",
    "date": "2026-02-27",
    "tldr": "When target mtime is newer, classify as conflict only if content differs; if source and target are hash-identical, treat as no-op.",
    "path": "doc/adr/ADR-20260227-0006-target-newer-conflict-hash-equivalence-exception.md"
  },
  {
    "id": "ADR-20260219-0005",
    "title": "Target-newer conflict deferred review in dedicated window",
    "tags": [
      "sync-task",
      "safety",
      "conflict-review",
      "watch-mode",
      "ux",
      "macos",
      "tauri"
    ],
    "status": "Accepted",
    "date": "2026-02-19",
    "tldr": "When target files are newer than source, skip auto-copy and defer handling to an explicit review session in a separate conflict-review window.",
    "path": "doc/adr/ADR-20260219-0005-target-newer-conflict-review-window.md"
  },
  {
    "id": "ADR-20260215-0004",
    "title": "Runtime watch-mode initial sync queue and concurrency limit",
    "tags": [
      "sync-task",
      "watch-mode",
      "runtime",
      "concurrency",
      "reliability",
      "macos"
    ],
    "status": "Accepted",
    "date": "2026-02-15",
    "tldr": "Runtime watch sync uses a bounded queue (max concurrency 2), coalesces watch events during active sync into one replay, and serializes overlapping runtime config applies.",
    "path": "doc/adr/ADR-20260215-0004-runtime-watch-sync-queue-and-concurrency.md"
  },
  {
    "id": "ADR-20260211-0003",
    "title": "Sync task target conflict policy, UUID runtime validation, and orphan cleanup workflow",
    "tags": [
      "sync-task",
      "safety",
      "watch-mode",
      "cleanup",
      "macos"
    ],
    "status": "Accepted",
    "date": "2026-02-11",
    "tldr": "Remove automatic target-side deletion, enforce source/target overlap constraints at runtime (including UUID sources), and replace deletion with explicit orphan scan and confirmed manual cleanup.",
    "path": "doc/adr/ADR-20260211-0003-sync-task-target-conflict-and-orphan-cleanup.md"
  },
  {
    "id": "ADR-20260210-0002",
    "title": "App lifecycle – background mode and system tray",
    "tags": [
      "lifecycle",
      "tray",
      "background",
      "cmd-quit",
      "macos"
    ],
    "status": "Accepted",
    "date": "2026-02-10",
    "tldr": "Keep window-close behavior stable under closeAction, add source-aware close events, and apply Cmd+Q-only confirmation policies.",
    "path": "doc/adr/ADR-20260210-0002-app-lifecycle-background-tray.md"
  },
  {
    "id": "ADR-20260209-0001-VFS",
    "title": "Dashboard volume enumeration uses macOS mount table",
    "tags": [
      "dashboard",
      "storage",
      "macos",
      "volume-discovery",
      "units"
    ],
    "status": "Accepted",
    "date": "2026-02-09",
    "tldr": "Replace /Volumes scanning with getmntinfo_r_np mount-table enumeration, keep network mounts capacity-unavailable, and standardize app-wide data-unit formatting.",
    "path": "doc/adr/ADR-20260209-0001-VFS-mount-table-volume-enumeration.md"
  }
]
